yafowil.widget.multiselect-1.4-py3.9-nspkg.pth
yafowil/widget/multiselect/__init__.py
yafowil/widget/multiselect/example.py
yafowil/widget/multiselect/tests.py
yafowil/widget/multiselect/widget.py
yafowil/widget/multiselect/resources/widget.css
yafowil/widget/multiselect/resources/widget.js
yafowil/widget/multiselect/resources/multi-select/LICENSE.txt
yafowil/widget/multiselect/resources/multi-select/README.markdown
yafowil/widget/multiselect/resources/multi-select/css/multi-select.css
yafowil/widget/multiselect/resources/multi-select/img/switch.png
yafowil/widget/multiselect/resources/multi-select/js/jquery.multi-select.js
yafowil_widget_multiselect-1.4.dist-info/licenses/LICENSE.rst
yafowil_widget_multiselect-1.4.dist-info/METADATA
yafowil_widget_multiselect-1.4.dist-info/WHEEL
yafowil_widget_multiselect-1.4.dist-info/entry_points.txt
yafowil_widget_multiselect-1.4.dist-info/namespace_packages.txt
yafowil_widget_multiselect-1.4.dist-info/top_level.txt
yafowil_widget_multiselect-1.4.dist-info/RECORD
