Metadata-Version: 2.4
Name: yafowil.widget.multiselect
Version: 1.4
Summary: multiselect widget for YAFOWIL
Home-page: http://github.com/conestack/yafowil.widget.multiselect
Author: Yafowil Contributors
Author-email: dev@conestack.org
License: Simplified BSD
Classifier: Environment :: Web Environment
Classifier: Operating System :: OS Independent
Classifier: Programming Language :: Python
Classifier: Topic :: Internet :: WWW/HTTP :: Dynamic Content
Classifier: License :: OSI Approved :: BSD License
Classifier: Programming Language :: Python :: 2.7
Classifier: Programming Language :: Python :: 3.5
Classifier: Programming Language :: Python :: 3.6
Classifier: Programming Language :: Python :: 3.7
License-File: LICENSE.rst
Requires-Dist: setuptools
Requires-Dist: yafowil<4.0.0,>2.1.99
Provides-Extra: test
Requires-Dist: yafowil[test]; extra == "test"
Dynamic: author
Dynamic: author-email
Dynamic: classifier
Dynamic: description
Dynamic: home-page
Dynamic: keywords
Dynamic: license
Dynamic: license-file
Dynamic: provides-extra
Dynamic: requires-dist
Dynamic: summary
